copick_mcp/__init__.py
copick_mcp/cli_introspection.py
copick_mcp/main.py
copick_mcp/cli/__init__.py
copick_mcp/cli/setup.py
copick_mcp-0.3.0.dist-info/METADATA
copick_mcp-0.3.0.dist-info/WHEEL
copick_mcp-0.3.0.dist-info/entry_points.txt
copick_mcp-0.3.0.dist-info/licenses/LICENSE
copick_mcp-0.3.0.dist-info/RECORD
