Metadata-Version: 2.4
Name: copick-mcp
Version: 0.3.0
Summary: MCP server for Copick.
Project-URL: Repository, https://github.com/copick/copick-mcp
Project-URL: Issues, https://github.com/copick/copick-mcp/issues
Project-URL: Documentation, https://github.com/copick/copick-mcp#readme
Author-email: Kyle Harrington <czi@kyleharrington.com>, "Utz H. Ermel" <utz@ermel.me>
License: MIT License
License-File: LICENSE
Keywords: annotation,copick,cryo-et,cryoet,mcp,model-context-protocol,tomography
Classifier: Development Status :: 3 - Alpha
Classifier: Intended Audience :: Developers
Classifier: License :: OSI Approved :: MIT License
Classifier: Operating System :: OS Independent
Classifier: Programming Language :: Python
Classifier: Programming Language :: Python :: 3
Classifier: Programming Language :: Python :: 3 :: Only
Classifier: Programming Language :: Python :: 3.9
Classifier: Programming Language :: Python :: 3.10
Classifier: Programming Language :: Python :: 3.11
Classifier: Programming Language :: Python :: 3.12
Classifier: Programming Language :: Python :: 3.13
Classifier: Programming Language :: Python :: Implementation :: CPython
Classifier: Programming Language :: Python :: Implementation :: PyPy
Requires-Python: >=3.9
Requires-Dist: click>=8.0
Requires-Dist: copick-torch
Requires-Dist: copick-utils
Requires-Dist: copick>=1.15.0
Requires-Dist: fastmcp>=0.1.0
Provides-Extra: dev
Requires-Dist: black>=25.1.0; extra == 'dev'
Requires-Dist: hatch-vcs>=0.4.0; extra == 'dev'
Requires-Dist: hatchling>=1.25.0; extra == 'dev'
Requires-Dist: ipython>=8.18.1; extra == 'dev'
Requires-Dist: pre-commit>=4.2.0; extra == 'dev'
Requires-Dist: ruff>=0.12.0; extra == 'dev'
Provides-Extra: test
Requires-Dist: pytest-cov>=6.2.1; extra == 'test'
Requires-Dist: pytest>=8.4.1; extra == 'test'
